TrueGIXERJ_Utils/__init__.py
TrueGIXERJ_Utils/colours.py
TrueGIXERJ_Utils/files.py
TrueGIXERJ_Utils/logger.py
truegixerj_utils-2025.2.27.dist-info/METADATA
truegixerj_utils-2025.2.27.dist-info/WHEEL
truegixerj_utils-2025.2.27.dist-info/licenses/LICENCE
truegixerj_utils-2025.2.27.dist-info/RECORD
