Metadata-Version: 2.4
Name: TrueGIXERJ_Utils
Version: 2025.2.27
Summary: a collection of small python utilities to use across various projects.
Author: TrueGIXERJ
License-Expression: GPL-3.0-only
License-File: LICENCE
Classifier: Operating System :: Microsoft :: Windows
Classifier: Programming Language :: Python :: 3
Requires-Python: >=3.12
